show_src_code/__init__.py
show_src_code/apps.py
show_src_code/includes.py
show_src_code/modals.py
show_src_code/source_code.py
show_src_code/urls.py
show_src_code/view_mixins.py
show_src_code/static/show_src_code/highlightjs.css
show_src_code/static/show_src_code/highlightjs.js
show_src_code/templatetags/__init__.py
show_src_code/templatetags/src_code.py
django_show_source_code-0.0.8.dist-info/LICENSE
django_show_source_code-0.0.8.dist-info/METADATA
django_show_source_code-0.0.8.dist-info/WHEEL
django_show_source_code-0.0.8.dist-info/top_level.txt
django_show_source_code-0.0.8.dist-info/RECORD
