Metadata-Version: 2.1
Name: django-show-source-code
Version: 0.0.8
Summary: Django app to show source code and templates in a bootstrap modal
Home-page: https://github.com/jonesim/show-src-code
Author: Ian Jones
License: UNKNOWN
Platform: UNKNOWN
Classifier: Programming Language :: Python :: 3
Classifier: License :: OSI Approved :: MIT License
Classifier: Operating System :: OS Independent
Requires-Python: >=3.6
Requires-Dist: django-ajax-helpers
Requires-Dist: django-nested-modals
Requires-Dist: requests
